odoo8_addon_stock_lot_scrap-8.0.1.0.0.99.dev7-nspkg.pth
odoo_addons/stock_lot_scrap/README.rst
odoo_addons/stock_lot_scrap/__init__.py
odoo_addons/stock_lot_scrap/__openerp__.py
odoo_addons/stock_lot_scrap/i18n/de.po
odoo_addons/stock_lot_scrap/i18n/es.po
odoo_addons/stock_lot_scrap/i18n/fr.po
odoo_addons/stock_lot_scrap/i18n/it.po
odoo_addons/stock_lot_scrap/i18n/sl.po
odoo_addons/stock_lot_scrap/i18n/stock_lot_scrap.pot
odoo_addons/stock_lot_scrap/models/__init__.py
odoo_addons/stock_lot_scrap/models/stock_scrap_lot.py
odoo_addons/stock_lot_scrap/static/description/icon.png
odoo_addons/stock_lot_scrap/tests/__init__.py
odoo_addons/stock_lot_scrap/tests/test_stock_lot_scrap.py
odoo8_addon_stock_lot_scrap-8.0.1.0.0.99.dev7.dist-info/METADATA
odoo8_addon_stock_lot_scrap-8.0.1.0.0.99.dev7.dist-info/WHEEL
odoo8_addon_stock_lot_scrap-8.0.1.0.0.99.dev7.dist-info/namespace_packages.txt
odoo8_addon_stock_lot_scrap-8.0.1.0.0.99.dev7.dist-info/top_level.txt
odoo8_addon_stock_lot_scrap-8.0.1.0.0.99.dev7.dist-info/RECORD
